bdiviz/__init__.py
bdiviz/api.py
bdiviz/utils.py
bdiviz/resource/gdc_table.csv
tests/__init__.py
bdi_viz-0.1.4.dist-info/LICENSE
bdi_viz-0.1.4.dist-info/METADATA
bdi_viz-0.1.4.dist-info/WHEEL
bdi_viz-0.1.4.dist-info/top_level.txt
bdi_viz-0.1.4.dist-info/RECORD
