Metadata-Version: 2.1
Name: bdi-viz
Version: 0.1.4
Summary: bdi-viz library
Home-page: https://github.com/VIDA-NYU/bdi-viz
Author: Eden Wu
Author-email: eden.wu@nyu.edu
Maintainer: Eden Wu
Maintainer-email: eden.wu@nyu.edu
License: Apache-2.0
Project-URL: Documentation, https://bdi-viz.readthedocs.io/en/latest/
Project-URL: Project Link, https://vida-nyu.github.io/BDF
Keywords: askem,data integration,nyu
Classifier: Development Status :: 5 - Production/Stable
Classifier: Intended Audience :: Science/Research
Classifier: License :: OSI Approved :: Apache Software License
Classifier: Topic :: Scientific/Engineering
License-File: LICENSE
Requires-Dist: altair ==5.5.0
Requires-Dist: bdi-kit ==0.4.0
Requires-Dist: bokeh ==3.4.3
Requires-Dist: datamart-profiler ==0.11
Requires-Dist: panel ==1.4.5
Requires-Dist: torch ==2.2.2
